{
  "project_info": {
    "project_number": "165327626441",
    "project_id": "chatapplication-9fd0d",
    "storage_bucket": "chatapplication-9fd0d.appspot.com"
  },
  "client": [
    {
      "client_info": {
        "mobilesdk_app_id": "1:165327626441:android:34e96b7594b68024f5ad18",
        "android_client_info": {
          "package_name": "com.example.chatapplication"
        }
      },
      "oauth_client": [],
      "api_key": [
        {
          "current_key": "AIzaSyBpF-_ejNbiVAhQS8xIEQMVuqcgvBZCnb4"
        }
      ],
      "services": {
        "appinvite_service": {
          "other_platform_oauth_client": []
        }
      }
    }
  ],
  "configuration_version": "1"
}